log/__init__.py
log/log.py
log_test/__init__.py
log_test/log_test.py
log_test-1.0.4.dist-info/LICENSE
log_test-1.0.4.dist-info/METADATA
log_test-1.0.4.dist-info/WHEEL
log_test-1.0.4.dist-info/top_level.txt
log_test-1.0.4.dist-info/RECORD
