Metadata-Version: 2.1
Name: log-test
Version: 1.0.4
Summary: A small print test log tool package
Home-page: https://github.com/ll51668/log
Author: Liu Li
Author-email: 657013040@qq.com
License: UNKNOWN
Platform: UNKNOWN
Classifier: Programming Language :: Python :: 2.7
Classifier: License :: OSI Approved :: MIT License
Classifier: Operating System :: OS Independent
